elemental/__init__.py
elemental/client.py
python_elemental-0.7.5.dist-info/WHEEL
python_elemental-0.7.5.dist-info/METADATA
python_elemental-0.7.5.dist-info/RECORD
