Metadata-Version: 2.1
Name: python-elemental
Version: 0.7.5
Summary: Python Client for Elemental On-Premises Appliances
Home-page: https://github.com/cbsinteractive/elemental.git
License: MIT
Author: CBS Interactive
Author-email: video-processing-team@cbsinteractive.com
Requires-Python: >=3.8,<4.0
Classifier: License :: OSI Approved :: MIT License
Classifier: Programming Language :: Python :: 3
Classifier: Programming Language :: Python :: 3.8
Classifier: Programming Language :: Python :: 3.9
Requires-Dist: requests (>=2.23,<3.0)
Requires-Dist: xmltodict (>=0.12.0,<0.13.0)
Project-URL: Repository, https://github.com/cbsinteractive/elemental.git
